Workbook

Sheet Monatsplan
A2: Zahlungsfortführung nach Datum
A3: Stand 25.09.2026 16:00 Uhr
A5: Monat oder Ansatz | B5: Anfang brutto | C5: Zufluss brutto | D5: Abfluss brutto | E5: Ende brutto
A6: 46266 | B6: =B12 -> 512400 | C6: 0 | D6: =IF($B$16=0,SUMIFS(Zahlungsregister!$G$6:$G$17,Zahlungsregister!$D$6:$D$17,1,Zahlungsregister!$C$6:$C$17,">="&MAX(A6,$B$14),Zahlungsregister!$C$6:$C$17,"<"&MIN(EDATE(A6,1),$B$15)),"Eingabe offen") -> 0 | E6: =IF(COUNT(B6:D6)=3,B6+C6-D6,"Eingabe offen") -> 512400
A7: 46296 | B7: =E6 -> 512400 | C7: 400000 | D7: =IF($B$16=0,SUMIFS(Zahlungsregister!$G$6:$G$17,Zahlungsregister!$D$6:$D$17,1,Zahlungsregister!$C$6:$C$17,">="&MAX(A7,$B$14),Zahlungsregister!$C$6:$C$17,"<"&MIN(EDATE(A7,1),$B$15)),"Eingabe offen") -> 499800 | E7: =IF(COUNT(B7:D7)=3,B7+C7-D7,"Eingabe offen") -> 412600
A8: 46327 | B8: =E7 -> 412600 | C8: 600000 | D8: =IF($B$16=0,SUMIFS(Zahlungsregister!$G$6:$G$17,Zahlungsregister!$D$6:$D$17,1,Zahlungsregister!$C$6:$C$17,">="&MAX(A8,$B$14),Zahlungsregister!$C$6:$C$17,"<"&MIN(EDATE(A8,1),$B$15)),"Eingabe offen") -> 511700 | E8: =IF(COUNT(B8:D8)=3,B8+C8-D8,"Eingabe offen") -> 500900
A9: 46357 | B9: =E8 -> 500900 | C9: 0 | D9: =IF($B$16=0,SUMIFS(Zahlungsregister!$G$6:$G$17,Zahlungsregister!$D$6:$D$17,1,Zahlungsregister!$C$6:$C$17,">="&MAX(A9,$B$14),Zahlungsregister!$C$6:$C$17,"<"&MIN(EDATE(A9,1),$B$15)),"Eingabe offen") -> 376040 | E9: =IF(COUNT(B9:D9)=3,B9+C9-D9,"Eingabe offen") -> 124860
A12: Bankbestand zum Stichtag | B12: 512400 | C12: 30 Finanzierung und 24 Bankansicht.
A13: Steuersatz | B13: 0.19 | C13: 19 Prozent laut Angebots- und Rechnungsbelegen.
A14: Plan beginnt am | B14: 46290 | C14: Inklusive dieses Tages; offene Zahlungen.
A15: Plan endet vor | B15: 46388 | C15: Exklusive dieses Tages.
A16: Unvollständige aktive Zeilen | B16: =COUNTIFS(Zahlungsregister!$D$6:$D$17,1,Zahlungsregister!$H$6:$H$17,"<>Freigegeben",Zahlungsregister!$H$6:$H$17,"<>Freigabe offen")+COUNTIFS(Zahlungsregister!$H$6:$H$17,"Planwahl prüfen")+IF(AND(Zahlungsregister!D13=1,Zahlungsregister!D15<>1),1,0) -> 0 | C16: Bei Fehlern bleibt der Monatsabfluss offen.
A17: Freigegebener Rest im Zeitraum | B17: =IF(B16=0,SUMIFS(Zahlungsregister!$G$6:$G$17,Zahlungsregister!$D$6:$D$17,1,Zahlungsregister!$E$6:$E$17,1,Zahlungsregister!$C$6:$C$17,">="&B14,Zahlungsregister!$C$6:$C$17,"<"&B15),"Eingabe offen") -> 0 | C17: Nur aktive Zeilen mit gesonderter Freigabe.
A18: Basisendbestand nach altem Plan | B18: 124860 | C18: 09 Ablauf und 30 Finanzierung; Stand 25.09.
A19: Änderung gegenüber Basis | B19: =IF(ISNUMBER(E9),E9-B18,"Eingabe offen") -> 0 | C19: Zeitverschiebung allein verändert den Endbestand nicht.
A20: Druckluftangebot netto | B20: 31750 | C20: 38 Angebot DR 260925.
A21: Bisheriger Druckluftansatz netto | B21: 30000 | C21: 13 Restkostenerhebung; im Grundplan enthalten.
A22: Der aktive Plan verwendet Zahlungsdaten und Bruttobeträge. Die alte Septemberreserve wird nicht zusätzlich abgezogen.
A23: Planbeträge sind keine Rechnungen. Das Register nennt für jede Position Einplanung und Freigabe getrennt.
A24: Abendleistungen in Zeile 13 erfordern auch Service in Zeile 15. Ohne Einplanung und Preis des Services bleibt der Gesamtplan offen.
A25: Weitere Kreditabrufe sind geplant. Vorsteuererstattungen sowie Miete der alten Produktion werden hier nicht als Baukontozufluss oder Bauinvestition erfasst.
A26: Die Mappe ergänzt Datei 09. Datei 10 bleibt die separate Sicht auf Nettoinvestition und Obligo. Ein positiver Bankbestand ist kein freies Kostenbudget.

Sheet Zahlungsregister
A2: Zahlungsansätze mit Einzelentscheidung
A3: Stand 25.09.2026 16:00 Uhr
A5: ID | B5: Netto EUR | C5: Datum geplant | D5: Einplanen 0/1 | E5: Freigabe 0/1 | F5: Bezahlt brutto | G5: Rest brutto | H5: Bearbeitung
A6: WH 260924 | B6: 160000 | C6: 46303 | D6: 1 | E6: 0 | F6: 0 | G6: =IF(A6="","",IF(AND(ISNUMBER(B6),B6>=0,ISNUMBER(F6),F6>=0,ISNUMBER(Monatsplan!B13),Monatsplan!B13>=0,Monatsplan!B13<=1,F6<=ROUND(B6*(1+Monatsplan!B13),2)),ROUND(B6*(1+Monatsplan!B13),2)-F6,"Betrag fehlt")) -> 190400 | H6: =IF(A6="","",IF(COUNTIFS($A$6:$A$17,A6)>1,"ID doppelt",IF(AND(D6<>0,D6<>1),"Planwahl prüfen",IF(AND(E6<>0,E6<>1),"Freigabe prüfen",IF(D6=0,"Nicht eingeplant",IF(NOT(ISNUMBER(C6)),"Datum fehlt",IF(OR(C6<Monatsplan!B14,C6>=Monatsplan!B15),"Außerhalb Zeitraum",IF(NOT(ISNUMBER(G6)),"Betrag fehlt",IF(E6=1,"Freigegeben","Freigabe offen"))))))))) -> Freigabe offen
A7: Plan Oktober | B7: 260000 | C7: 46325 | D7: 1 | E7: 0 | F7: 0 | G7: =IF(A7="","",IF(AND(ISNUMBER(B7),B7>=0,ISNUMBER(F7),F7>=0,ISNUMBER(Monatsplan!B13),Monatsplan!B13>=0,Monatsplan!B13<=1,F7<=ROUND(B7*(1+Monatsplan!B13),2)),ROUND(B7*(1+Monatsplan!B13),2)-F7,"Betrag fehlt")) -> 309400 | H7: =IF(A7="","",IF(COUNTIFS($A$6:$A$17,A7)>1,"ID doppelt",IF(AND(D7<>0,D7<>1),"Planwahl prüfen",IF(AND(E7<>0,E7<>1),"Freigabe prüfen",IF(D7=0,"Nicht eingeplant",IF(NOT(ISNUMBER(C7)),"Datum fehlt",IF(OR(C7<Monatsplan!B14,C7>=Monatsplan!B15),"Außerhalb Zeitraum",IF(NOT(ISNUMBER(G7)),"Betrag fehlt",IF(E7=1,"Freigegeben","Freigabe offen"))))))))) -> Freigabe offen
A8: Plan November | B8: 430000 | C8: 46356 | D8: 1 | E8: 0 | F8: 0 | G8: =IF(A8="","",IF(AND(ISNUMBER(B8),B8>=0,ISNUMBER(F8),F8>=0,ISNUMBER(Monatsplan!B13),Monatsplan!B13>=0,Monatsplan!B13<=1,F8<=ROUND(B8*(1+Monatsplan!B13),2)),ROUND(B8*(1+Monatsplan!B13),2)-F8,"Betrag fehlt")) -> 511700 | H8: =IF(A8="","",IF(COUNTIFS($A$6:$A$17,A8)>1,"ID doppelt",IF(AND(D8<>0,D8<>1),"Planwahl prüfen",IF(AND(E8<>0,E8<>1),"Freigabe prüfen",IF(D8=0,"Nicht eingeplant",IF(NOT(ISNUMBER(C8)),"Datum fehlt",IF(OR(C8<Monatsplan!B14,C8>=Monatsplan!B15),"Außerhalb Zeitraum",IF(NOT(ISNUMBER(G8)),"Betrag fehlt",IF(E8=1,"Freigegeben","Freigabe offen"))))))))) -> Freigabe offen
A9: Plan Dezember | B9: 316000 | C9: 46387 | D9: 1 | E9: 0 | F9: 0 | G9: =IF(A9="","",IF(AND(ISNUMBER(B9),B9>=0,ISNUMBER(F9),F9>=0,ISNUMBER(Monatsplan!B13),Monatsplan!B13>=0,Monatsplan!B13<=1,F9<=ROUND(B9*(1+Monatsplan!B13),2)),ROUND(B9*(1+Monatsplan!B13),2)-F9,"Betrag fehlt")) -> 376040 | H9: =IF(A9="","",IF(COUNTIFS($A$6:$A$17,A9)>1,"ID doppelt",IF(AND(D9<>0,D9<>1),"Planwahl prüfen",IF(AND(E9<>0,E9<>1),"Freigabe prüfen",IF(D9=0,"Nicht eingeplant",IF(NOT(ISNUMBER(C9)),"Datum fehlt",IF(OR(C9<Monatsplan!B14,C9>=Monatsplan!B15),"Außerhalb Zeitraum",IF(NOT(ISNUMBER(G9)),"Betrag fehlt",IF(E9=1,"Freigegeben","Freigabe offen"))))))))) -> Freigabe offen
A10: MB Voraus | B10: 10800 | C10: 46293 | D10: 0 | E10: 0 | F10: 0 | G10: =IF(A10="","",IF(AND(ISNUMBER(B10),B10>=0,ISNUMBER(F10),F10>=0,ISNUMBER(Monatsplan!B13),Monatsplan!B13>=0,Monatsplan!B13<=1,F10<=ROUND(B10*(1+Monatsplan!B13),2)),ROUND(B10*(1+Monatsplan!B13),2)-F10,"Betrag fehlt")) -> 12852 | H10: =IF(A10="","",IF(COUNTIFS($A$6:$A$17,A10)>1,"ID doppelt",IF(AND(D10<>0,D10<>1),"Planwahl prüfen",IF(AND(E10<>0,E10<>1),"Freigabe prüfen",IF(D10=0,"Nicht eingeplant",IF(NOT(ISNUMBER(C10)),"Datum fehlt",IF(OR(C10<Monatsplan!B14,C10>=Monatsplan!B15),"Außerhalb Zeitraum",IF(NOT(ISNUMBER(G10)),"Betrag fehlt",IF(E10=1,"Freigegeben","Freigabe offen"))))))))) -> Nicht eingeplant
A11: MB Rest | B11: 25200 | C11: 46356 | D11: 0 | E11: 0 | F11: 0 | G11: =IF(A11="","",IF(AND(ISNUMBER(B11),B11>=0,ISNUMBER(F11),F11>=0,ISNUMBER(Monatsplan!B13),Monatsplan!B13>=0,Monatsplan!B13<=1,F11<=ROUND(B11*(1+Monatsplan!B13),2)),ROUND(B11*(1+Monatsplan!B13),2)-F11,"Betrag fehlt")) -> 29988 | H11: =IF(A11="","",IF(COUNTIFS($A$6:$A$17,A11)>1,"ID doppelt",IF(AND(D11<>0,D11<>1),"Planwahl prüfen",IF(AND(E11<>0,E11<>1),"Freigabe prüfen",IF(D11=0,"Nicht eingeplant",IF(NOT(ISNUMBER(C11)),"Datum fehlt",IF(OR(C11<Monatsplan!B14,C11>=Monatsplan!B15),"Außerhalb Zeitraum",IF(NOT(ISNUMBER(G11)),"Betrag fehlt",IF(E11=1,"Freigegeben","Freigabe offen"))))))))) -> Nicht eingeplant
A12: KM N03 | B12: 9600 | D12: 0 | E12: 0 | F12: 0 | G12: =IF(A12="","",IF(AND(ISNUMBER(B12),B12>=0,ISNUMBER(F12),F12>=0,ISNUMBER(Monatsplan!B13),Monatsplan!B13>=0,Monatsplan!B13<=1,F12<=ROUND(B12*(1+Monatsplan!B13),2)),ROUND(B12*(1+Monatsplan!B13),2)-F12,"Betrag fehlt")) -> 11424 | H12: =IF(A12="","",IF(COUNTIFS($A$6:$A$17,A12)>1,"ID doppelt",IF(AND(D12<>0,D12<>1),"Planwahl prüfen",IF(AND(E12<>0,E12<>1),"Freigabe prüfen",IF(D12=0,"Nicht eingeplant",IF(NOT(ISNUMBER(C12)),"Datum fehlt",IF(OR(C12<Monatsplan!B14,C12>=Monatsplan!B15),"Außerhalb Zeitraum",IF(NOT(ISNUMBER(G12)),"Betrag fehlt",IF(E12=1,"Freigegeben","Freigabe offen"))))))))) -> Nicht eingeplant
A13: Abend Breden | B13: 7730 | C13: 46356 | D13: 0 | E13: 0 | F13: 0 | G13: =IF(A13="","",IF(AND(ISNUMBER(B13),B13>=0,ISNUMBER(F13),F13>=0,ISNUMBER(Monatsplan!B13),Monatsplan!B13>=0,Monatsplan!B13<=1,F13<=ROUND(B13*(1+Monatsplan!B13),2)),ROUND(B13*(1+Monatsplan!B13),2)-F13,"Betrag fehlt")) -> 9198.7 | H13: =IF(A13="","",IF(COUNTIFS($A$6:$A$17,A13)>1,"ID doppelt",IF(AND(D13<>0,D13<>1),"Planwahl prüfen",IF(AND(E13<>0,E13<>1),"Freigabe prüfen",IF(D13=0,"Nicht eingeplant",IF(NOT(ISNUMBER(C13)),"Datum fehlt",IF(OR(C13<Monatsplan!B14,C13>=Monatsplan!B15),"Außerhalb Zeitraum",IF(NOT(ISNUMBER(G13)),"Betrag fehlt",IF(E13=1,"Freigegeben","Freigabe offen"))))))))) -> Nicht eingeplant
A14: DR Mehransatz | B14: =IF(AND(COUNT(Monatsplan!B20:B21)=2,MIN(Monatsplan!B20:B21)>=0),Monatsplan!B20-Monatsplan!B21,"Angebot fehlt") -> 1750 | C14: 46356 | D14: 0 | E14: 0 | F14: 0 | G14: =IF(A14="","",IF(AND(ISNUMBER(B14),B14>=0,ISNUMBER(F14),F14>=0,ISNUMBER(Monatsplan!B13),Monatsplan!B13>=0,Monatsplan!B13<=1,F14<=ROUND(B14*(1+Monatsplan!B13),2)),ROUND(B14*(1+Monatsplan!B13),2)-F14,"Betrag fehlt")) -> 2082.5 | H14: =IF(A14="","",IF(COUNTIFS($A$6:$A$17,A14)>1,"ID doppelt",IF(AND(D14<>0,D14<>1),"Planwahl prüfen",IF(AND(E14<>0,E14<>1),"Freigabe prüfen",IF(D14=0,"Nicht eingeplant",IF(NOT(ISNUMBER(C14)),"Datum fehlt",IF(OR(C14<Monatsplan!B14,C14>=Monatsplan!B15),"Außerhalb Zeitraum",IF(NOT(ISNUMBER(G14)),"Betrag fehlt",IF(E14=1,"Freigegeben","Freigabe offen"))))))))) -> Nicht eingeplant
A15: Service Abend | D15: 0 | E15: 0 | F15: 0 | G15: =IF(A15="","",IF(AND(ISNUMBER(B15),B15>=0,ISNUMBER(F15),F15>=0,ISNUMBER(Monatsplan!B13),Monatsplan!B13>=0,Monatsplan!B13<=1,F15<=ROUND(B15*(1+Monatsplan!B13),2)),ROUND(B15*(1+Monatsplan!B13),2)-F15,"Betrag fehlt")) -> Betrag fehlt | H15: =IF(A15="","",IF(COUNTIFS($A$6:$A$17,A15)>1,"ID doppelt",IF(AND(D15<>0,D15<>1),"Planwahl prüfen",IF(AND(E15<>0,E15<>1),"Freigabe prüfen",IF(D15=0,"Nicht eingeplant",IF(NOT(ISNUMBER(C15)),"Datum fehlt",IF(OR(C15<Monatsplan!B14,C15>=Monatsplan!B15),"Außerhalb Zeitraum",IF(NOT(ISNUMBER(G15)),"Betrag fehlt",IF(E15=1,"Freigegeben","Freigabe offen"))))))))) -> Nicht eingeplant
G16: =IF(A16="","",IF(AND(ISNUMBER(B16),B16>=0,ISNUMBER(F16),F16>=0,ISNUMBER(Monatsplan!B13),Monatsplan!B13>=0,Monatsplan!B13<=1,F16<=ROUND(B16*(1+Monatsplan!B13),2)),ROUND(B16*(1+Monatsplan!B13),2)-F16,"Betrag fehlt")) | H16: =IF(A16="","",IF(COUNTIFS($A$6:$A$17,A16)>1,"ID doppelt",IF(AND(D16<>0,D16<>1),"Planwahl prüfen",IF(AND(E16<>0,E16<>1),"Freigabe prüfen",IF(D16=0,"Nicht eingeplant",IF(NOT(ISNUMBER(C16)),"Datum fehlt",IF(OR(C16<Monatsplan!B14,C16>=Monatsplan!B15),"Außerhalb Zeitraum",IF(NOT(ISNUMBER(G16)),"Betrag fehlt",IF(E16=1,"Freigegeben","Freigabe offen")))))))))
G17: =IF(A17="","",IF(AND(ISNUMBER(B17),B17>=0,ISNUMBER(F17),F17>=0,ISNUMBER(Monatsplan!B13),Monatsplan!B13>=0,Monatsplan!B13<=1,F17<=ROUND(B17*(1+Monatsplan!B13),2)),ROUND(B17*(1+Monatsplan!B13),2)-F17,"Betrag fehlt")) | H17: =IF(A17="","",IF(COUNTIFS($A$6:$A$17,A17)>1,"ID doppelt",IF(AND(D17<>0,D17<>1),"Planwahl prüfen",IF(AND(E17<>0,E17<>1),"Freigabe prüfen",IF(D17=0,"Nicht eingeplant",IF(NOT(ISNUMBER(C17)),"Datum fehlt",IF(OR(C17<Monatsplan!B14,C17>=Monatsplan!B15),"Außerhalb Zeitraum",IF(NOT(ISNUMBER(G17)),"Betrag fehlt",IF(E17=1,"Freigegeben","Freigabe offen")))))))))
A20: Zeilen 6 bis 9: 21 Zahlungsplan und 37 Rechnungseingang. Der offene Septemberabschlag ist genau einmal am 08.10. eingeplant.
A21: Zeilen 10 und 11: 18 MB 0925. 10.800 EUR Vorauszahlung und 25.200 EUR Rest bleiben ohne Auftrag außerhalb des aktiven Plans.
A22: Zeilen 12 und 13: 15 Kranangebot und 34 Ergänzungsangebot. Krantermin fehlt; Abendpreis umfasst keinen Maschinenservice.
A23: Zeilen 14 und 15: 38 und 39 Druckluft (31.750 minus 30.000 EUR) sowie 40 Maschinenbauer (Preis fehlt).
A24: Gelb = Eingabe. Einplanen ist eine Prognoseentscheidung. Freigabe ist eine separate Entscheidung und löst keine Bankzahlung aus.
A25: Leere Zeilen 16 und 17 sind für weitere Vorgänge vorbereitet. ID, Betrag, Datum, 0/1-Werte und bezahlt = 0 eingeben. Formeln bleiben stehen.
A26: Bei weiteren Zeilen nach 17 müssen Formeln und die begrenzten Auswertungsbereiche 6 bis 17 erweitert werden. IDs dürfen nicht doppelt vergeben sein.
A27: Bei Fortschreibung des Kontostichtags Anfangssaldo und bisher bezahlte Anteile zusammen aktualisieren. Frühere Ausgaben nicht nochmals vom neuen Saldo abziehen.
A28: Die Druckluftdifferenz verändert bei Einplanung den alten Restansatz. Die gesamten 31.750 EUR dürfen nicht zusätzlich zum unveränderten Grundplan angesetzt werden.
