Workbook

Sheet Honorar
A2: Honorarzuordnung und Leistungsanteile
A3: Hartwig Architektur · 05.10.2026 · Vertragspauschale, keine neue Honorarschlussrechnung
A5: Pauschale Grundleistungen | C5: 48000 | G5: 02, Abschnitt 2
A7: Leistungsphase | B7: Vertragsanteil | C7: Pauschale EUR | D7: Rechenanteil | E7: Ansatz EUR | F7: Rest EUR | G7: Belegstatus
A8: 1 Grundlagen | B8: 0.02 | C8: =IF(AND(ISNUMBER($C$5),ISNUMBER(B8),B8>=0,B8<=1),ROUND($C$5*B8,2),"Eingabe fehlt") -> 960 | D8: 1 | E8: =IF(OR(NOT(ISNUMBER(C8)),NOT(ISNUMBER(D8)),D8<0,D8>1),"Anteil prüfen",ROUND(C8*D8,2)) -> 960 | F8: =IF(AND(ISNUMBER(C8),ISNUMBER(E8)),C8-E8,"Offen") -> 0 | G8: =Leistungsbelege!D8 -> Belegt
A9: 2 Vorplanung | B9: 0.07 | C9: =IF(AND(ISNUMBER($C$5),ISNUMBER(B9),B9>=0,B9<=1),ROUND($C$5*B9,2),"Eingabe fehlt") -> 3360 | D9: 1 | E9: =IF(OR(NOT(ISNUMBER(C9)),NOT(ISNUMBER(D9)),D9<0,D9>1),"Anteil prüfen",ROUND(C9*D9,2)) -> 3360 | F9: =IF(AND(ISNUMBER(C9),ISNUMBER(E9)),C9-E9,"Offen") -> 0 | G9: =Leistungsbelege!D9 -> Belegt
A10: 3 Entwurf | B10: 0.15 | C10: =IF(AND(ISNUMBER($C$5),ISNUMBER(B10),B10>=0,B10<=1),ROUND($C$5*B10,2),"Eingabe fehlt") -> 7200 | D10: 1 | E10: =IF(OR(NOT(ISNUMBER(C10)),NOT(ISNUMBER(D10)),D10<0,D10>1),"Anteil prüfen",ROUND(C10*D10,2)) -> 7200 | F10: =IF(AND(ISNUMBER(C10),ISNUMBER(E10)),C10-E10,"Offen") -> 0 | G10: =Leistungsbelege!D10 -> Belegt
A11: 4 Genehmigung | B11: 0.03 | C11: =IF(AND(ISNUMBER($C$5),ISNUMBER(B11),B11>=0,B11<=1),ROUND($C$5*B11,2),"Eingabe fehlt") -> 1440 | D11: 1 | E11: =IF(OR(NOT(ISNUMBER(C11)),NOT(ISNUMBER(D11)),D11<0,D11>1),"Anteil prüfen",ROUND(C11*D11,2)) -> 1440 | F11: =IF(AND(ISNUMBER(C11),ISNUMBER(E11)),C11-E11,"Offen") -> 0 | G11: =Leistungsbelege!D11 -> Belegt
A12: 5 Ausführung | B12: 0.25 | C12: =IF(AND(ISNUMBER($C$5),ISNUMBER(B12),B12>=0,B12<=1),ROUND($C$5*B12,2),"Eingabe fehlt") -> 12000 | D12: 1 | E12: =IF(OR(NOT(ISNUMBER(C12)),NOT(ISNUMBER(D12)),D12<0,D12>1),"Anteil prüfen",ROUND(C12*D12,2)) -> 12000 | F12: =IF(AND(ISNUMBER(C12),ISNUMBER(E12)),C12-E12,"Offen") -> 0 | G12: =Leistungsbelege!D12 -> Rückfrage
A13: 6 LV und Mengen | B13: 0.1 | C13: =IF(AND(ISNUMBER($C$5),ISNUMBER(B13),B13>=0,B13<=1),ROUND($C$5*B13,2),"Eingabe fehlt") -> 4800 | D13: 1 | E13: =IF(OR(NOT(ISNUMBER(C13)),NOT(ISNUMBER(D13)),D13<0,D13>1),"Anteil prüfen",ROUND(C13*D13,2)) -> 4800 | F13: =IF(AND(ISNUMBER(C13),ISNUMBER(E13)),C13-E13,"Offen") -> 0 | G13: =Leistungsbelege!D13 -> Belegt
A14: 7 Vergabe | B14: 0.04 | C14: =IF(AND(ISNUMBER($C$5),ISNUMBER(B14),B14>=0,B14<=1),ROUND($C$5*B14,2),"Eingabe fehlt") -> 1920 | D14: 1 | E14: =IF(OR(NOT(ISNUMBER(C14)),NOT(ISNUMBER(D14)),D14<0,D14>1),"Anteil prüfen",ROUND(C14*D14,2)) -> 1920 | F14: =IF(AND(ISNUMBER(C14),ISNUMBER(E14)),C14-E14,"Offen") -> 0 | G14: =Leistungsbelege!D14 -> Belegt
A15: 8 Überwachung | B15: 0.32 | C15: =IF(AND(ISNUMBER($C$5),ISNUMBER(B15),B15>=0,B15<=1),ROUND($C$5*B15,2),"Eingabe fehlt") -> 15360 | D15: 1 | E15: =IF(OR(NOT(ISNUMBER(C15)),NOT(ISNUMBER(D15)),D15<0,D15>1),"Anteil prüfen",ROUND(C15*D15,2)) -> 15360 | F15: =IF(AND(ISNUMBER(C15),ISNUMBER(E15)),C15-E15,"Offen") -> 0 | G15: =Leistungsbelege!D15 -> Rückfrage
A16: 9 Betreuung | B16: 0.02 | C16: =IF(AND(ISNUMBER($C$5),ISNUMBER(B16),B16>=0,B16<=1),ROUND($C$5*B16,2),"Eingabe fehlt") -> 960 | D16: 0 | E16: =IF(OR(NOT(ISNUMBER(C16)),NOT(ISNUMBER(D16)),D16<0,D16>1),"Anteil prüfen",ROUND(C16*D16,2)) -> 0 | F16: =IF(AND(ISNUMBER(C16),ISNUMBER(E16)),C16-E16,"Offen") -> 960 | G16: =Leistungsbelege!D16 -> Laufend
A18: Grundleistungen | B18: =IF(COUNT(B8:B16)=9,SUM(B8:B16),"Anteil prüfen") -> 1 | C18: =IF(AND(COUNT(C8:C16)=9,ABS(SUM(B8:B16)-1)<0.000001),SUM(C8:C16),"Vertrag prüfen") -> 48000 | E18: =IF(OR(COUNT(E8:E16)<>9,NOT(ISNUMBER(C18))),"Anteil prüfen",SUM(E8:E16)) -> 47040 | F18: =IF(AND(ISNUMBER(C18),ISNUMBER(E18)),C18-E18,"Offen") -> 960
A19: Bestandsarbeiten | C19: 3000 | E19: =IF(ISNUMBER(C19),C19,"Eingabe fehlt") -> 3000 | G19: 02 und 04, gesonderte Pauschale
A20: Nebenkosten | C20: 3000 | E20: =IF(ISNUMBER(C20),C20,"Eingabe fehlt") -> 3000 | G20: 02, pauschal vereinbart
A22: Gesamt netto | C22: =IF(COUNT(C18:C20)=3,SUM(C18:C20),"Eingabe fehlt") -> 54000 | E22: =IF(NOT(ISNUMBER(E18)),"Anteil prüfen",IF(COUNT(E18:E20)=3,SUM(E18:E20),"Eingabe fehlt")) -> 53040 | F22: =IF(AND(ISNUMBER(C22),ISNUMBER(E22)),C22-E22,"Offen") -> 960
A23: Umsatzsteuer | B23: 0.19 | E23: =IF(AND(ISNUMBER(E22),ISNUMBER(B23)),ROUND(E22*B23,2),"Offen") -> 10077.6
A24: Ansatz brutto | E24: =IF(ISNUMBER(E23),E22+E23,"Offen") -> 63117.6
A26: Offene Belegfragen | G26: =COUNTIFS(Leistungsbelege!D8:D16,"<>Belegt") -> 3
A28: Gelbe Rechenanteile sind Annahmen zur Pauschalzuordnung, keine Abnahme oder Fälligkeitsentscheidung.
A30: 100 Prozent in Phase 8 schließt die offenen Belegfragen nicht. Rückfragen stehen unabhängig im rechten Blatt.
A32: Ausgangsstand wie 37/40: 53.040,00 EUR netto zugeordnet; 960,00 EUR für laufende Betreuung verbleiben.

Sheet Leistungsbelege
A2: Leistungsbelege und offene Fragen
A3: Grundlage: Vertrag 02, Erläuterung 52 und vorhandene Projektunterlagen.
A7: Phase | B7: Beleg und konkretes Ergebnis | C7: Offene Frage | D7: Status
A8: 1 | B8: 03/04: Untersuchungsbedarf und Bestandsaufnahme. | C8: Zusatzleistung Bestand separat vergütet. | D8: Belegt
A9: 2 | B9: 05/06: Variantenvergleich und Nordanbauentscheidung. | C9: Keine weitere Umnutzungsvariante beauftragt. | D9: Belegt
A10: 3 | B10: 07–10: Entwurf, Kosten und Fachplanerabstimmung. | C10: Gebührenansatz in 09 ist frühe Steuerpauschale. | D10: Belegt
A11: 4 | B11: 11–17: Antrag, Ergänzung und Bescheid. | C11: Späterer Gymnastikwunsch ist nicht mit umfasst. | D11: Belegt
A12: 5 | B12: 18–22: Abruf, AP-01, D-12 und Portalstände. | C12: Auflösung abweichender Höheninformation prüfen. | D12: Rückfrage
A13: 6 | B13: 23/24: zwölf LV-Positionen mit Mengen und Preisen. | C13: Kein Nachweis der tatsächlichen Ausführung allein durch LV. | D13: Belegt
A14: 7 | B14: 25–28: Angebote, Preisspiegel und Zuschlag. | C14: Nachtrag N01 wurde nur teilweise beauftragt. | D14: Belegt
A15: 8 | B15: 30/35–40: Bauablauf, Aufmaß, Prüfung und Übergabe. | C15: Einzelblatt Nachkontrolle und Architekturabnahme fehlen. | D15: Rückfrage
A16: 9 | B16: 41–44/50/51: Begehung, Bewertung und Untersuchungsvorschlag. | C16: Ursache offen; weitere Betreuung und Kontrollbegehung stehen aus. | D16: Laufend
A19: 1 Bedienung
A20: Status nur nach Belegabgleich ändern. Eine hohe Prozentzahl im Honorarblatt schließt keine Belegfrage.
A22: 2 Vertragsgrundlage
A23: 02 vereinbart 48.000 EUR für Grundleistungen sowie jeweils 3.000 EUR für Bestand und Nebenkosten.
A25: 3 Grenzen
A26: Kein Saldo aus Rechnungen und Zahlungen. Keine automatische Honoraranpassung anhand der Baukosten.
A28: Die Unterlage 52 erläutert die einzelnen Ergebnisse. Die Zuordnung behauptet keine lückenlose Überwachung.
