Workbook

Sheet Finanzierung
A2: Projektfinanzierung und Vermietungsannahmen
A3: SW-HI-26-08 · Beträge in EUR
A5: Ansatz / Ergebnis | B5: Wert | C5: Grundlage
A6: Projektkosten Ausgang | B6: 3463770.4 | C6: Kostenansätze aus Einzelbelegen; ohne Nachtrag/Korrektur
A7: Nachtrag und Entgeltminderung | B7: 18445 | C7: 105 Rohbau / 106 Innenausbau
A8: Projektkosten fortgeschrieben | B8: =SUM(B6:B7) -> 3482215.4 | C8: Summe aus den beiden vorstehenden Ansätzen
A9: Eigenkapital | B9: 2100000 | C9: 108 Gesellschafterbeschluss
A10: Darlehen | B10: 1600000 | C10: 107 Darlehensvereinbarung
A11: Finanzierungsmittel | B11: =SUM(B9:B10) -> 3700000 | C11: Eigenkapital und Darlehen
A12: Mittel nach Projektkosten | B12: =B11-B8 -> 217784.59 | C12: Finanzierungsmittel abzüglich Projektkosten
A13: Sollzins p. a. | B13: 0.036 | C13: 107 Darlehensvereinbarung ab 2029
A14: Anfängliche Tilgung p. a. | B14: 0.015 | C14: 107 Darlehensvereinbarung ab 2029
A15: Annuität volles Jahr | B15: =B10*SUM(B13:B14) -> 81600 | C15: Anfängliche Zinsen plus anfängliche Tilgung
A16: Leerstand / Mietausfall | B16: 0 | C16: Annahme; Anteil der möglichen Jahreskaltmiete
A17: Nicht umlagefähige Kosten p. a. | B17: 18000 | C17: 108 Planannahme; keine bereits angefallenen Kosten
A18: Miete volles Jahr vor Ausfall | B18: =Vermietung!F14 -> 102000 | C18: Vermietung: Wohnungs- und Stellplatzkaltmieten
A19: Miete nach Ausfall | B19: =IF(AND(ISNUMBER(B18),ISNUMBER(B16)),B18*(1-B16),"offen") -> 102000 | C19: Mögliche Miete mal vermieteter Anteil
A20: Ergebnis vor Finanzierung | B20: =IF(AND(ISNUMBER(B19),ISNUMBER(B17)),B19-B17,"offen") -> 84000 | C20: Miete nach Ausfall abzüglich laufender Kosten
A21: Jährlicher Schuldendienst | B21: =B15 -> 81600 | C21: Annuität ab Januar 2029
A22: Liquidität vor Ertragsteuern | B22: =IF(ISNUMBER(B20),B20-B21,"offen") -> 2400 | C22: Laufendes Ergebnis abzüglich Schuldendienst
A23: Schuldendienstdeckung | B23: =IF(AND(ISNUMBER(B20),B21>0),B20/B21,"offen") -> 1.0294118 | C23: Ergebnis vor Finanzierung / Schuldendienst
A25: Planjahr 2029 bei ganzjähriger Vermietung. Keine Aussage zur zulässigen Miethöhe.
A26: Keine Betriebs-/Heizkostenvorauszahlungen und keine Kautionen als Ertrag gerechnet.
A27: AfA, Ertragsteuern und spätere Anschlussfinanzierung sind hier nicht modelliert.

Sheet Vermietung
A2: Vermietung · volles Planjahr
A3: SW-HI-26-08 · Beträge in EUR
A5: Wohnung | B5: Wohnfläche m² | C5: EUR je m² | D5: Wohnung mtl. | E5: Stellplatz mtl. | F5: Jahresmiete
A6: WE 01 | B6: 68 | C6: 13.5 | D6: =IF(COUNT(B6:C6)=2,B6*C6,"offen") -> 918 | E6: 50 | F6: =IF(COUNT(D6:E6)=2,SUM(D6:E6)*12,"offen") -> 11616
A7: WE 02 | B7: 75 | C7: 13.5 | D7: =IF(COUNT(B7:C7)=2,B7*C7,"offen") -> 1012.5 | E7: 50 | F7: =IF(COUNT(D7:E7)=2,SUM(D7:E7)*12,"offen") -> 12750
A8: WE 03 | B8: 82 | C8: 13.5 | D8: =IF(COUNT(B8:C8)=2,B8*C8,"offen") -> 1107 | E8: 50 | F8: =IF(COUNT(D8:E8)=2,SUM(D8:E8)*12,"offen") -> 13884
A9: WE 04 | B9: 68 | C9: 13.5 | D9: =IF(COUNT(B9:C9)=2,B9*C9,"offen") -> 918 | E9: 50 | F9: =IF(COUNT(D9:E9)=2,SUM(D9:E9)*12,"offen") -> 11616
A10: WE 05 | B10: 75 | C10: 13.5 | D10: =IF(COUNT(B10:C10)=2,B10*C10,"offen") -> 1012.5 | E10: 50 | F10: =IF(COUNT(D10:E10)=2,SUM(D10:E10)*12,"offen") -> 12750
A11: WE 06 | B11: 82 | C11: 13.5 | D11: =IF(COUNT(B11:C11)=2,B11*C11,"offen") -> 1107 | E11: 50 | F11: =IF(COUNT(D11:E11)=2,SUM(D11:E11)*12,"offen") -> 13884
A12: WE 07 | B12: 75 | C12: 13.5 | D12: =IF(COUNT(B12:C12)=2,B12*C12,"offen") -> 1012.5 | E12: 50 | F12: =IF(COUNT(D12:E12)=2,SUM(D12:E12)*12,"offen") -> 12750
A13: WE 08 | B13: 75 | C13: 13.5 | D13: =IF(COUNT(B13:C13)=2,B13*C13,"offen") -> 1012.5 | E13: 50 | F13: =IF(COUNT(D13:E13)=2,SUM(D13:E13)*12,"offen") -> 12750
A14: Summe | B14: =SUM(B6:B13) -> 600 | D14: =IF(COUNT(D6:D13)=8,SUM(D6:D13),"offen") -> 8100 | E14: =SUM(E6:E13) -> 400 | F14: =IF(COUNT(F6:F13)=8,SUM(F6:F13),"offen") -> 102000
A17: Quelle: 108 Gesellschafterbeschluss und Vermietungsannahmen.
A18: Die acht Stellplätze sind den acht Wohnungen zugeordnet.

Sheet Tilgung
A2: Darlehensplan 2029 bis 2033
A3: SW-HI-26-08 · Beträge in EUR
A5: Monat | B5: Anfangsschuld | C5: Annuität | D5: Zinsen | E5: Tilgung | F5: Restschuld
A6: 47119 | B6: =Finanzierung!B10 -> 1600000 | C6: =MIN(B6+D6,Finanzierung!$B$15/12) -> 6800 | D6: =ROUND(B6*Finanzierung!$B$13/12,2) -> 4800 | E6: =C6-D6 -> 2000 | F6: =B6-E6 -> 1598000
A7: 47150 | B7: =F6 -> 1598000 | C7: =MIN(B7+D7,Finanzierung!$B$15/12) -> 6800 | D7: =ROUND(B7*Finanzierung!$B$13/12,2) -> 4794 | E7: =C7-D7 -> 2006 | F7: =B7-E7 -> 1595994
A8: 47178 | B8: =F7 -> 1595994 | C8: =MIN(B8+D8,Finanzierung!$B$15/12) -> 6800 | D8: =ROUND(B8*Finanzierung!$B$13/12,2) -> 4787.98 | E8: =C8-D8 -> 2012.02 | F8: =B8-E8 -> 1593982
A9: 47209 | B9: =F8 -> 1593982 | C9: =MIN(B9+D9,Finanzierung!$B$15/12) -> 6800 | D9: =ROUND(B9*Finanzierung!$B$13/12,2) -> 4781.95 | E9: =C9-D9 -> 2018.05 | F9: =B9-E9 -> 1591963.9
A10: 47239 | B10: =F9 -> 1591963.9 | C10: =MIN(B10+D10,Finanzierung!$B$15/12) -> 6800 | D10: =ROUND(B10*Finanzierung!$B$13/12,2) -> 4775.89 | E10: =C10-D10 -> 2024.11 | F10: =B10-E10 -> 1589939.8
A11: 47270 | B11: =F10 -> 1589939.8 | C11: =MIN(B11+D11,Finanzierung!$B$15/12) -> 6800 | D11: =ROUND(B11*Finanzierung!$B$13/12,2) -> 4769.82 | E11: =C11-D11 -> 2030.18 | F11: =B11-E11 -> 1587909.6
A12: 47300 | B12: =F11 -> 1587909.6 | C12: =MIN(B12+D12,Finanzierung!$B$15/12) -> 6800 | D12: =ROUND(B12*Finanzierung!$B$13/12,2) -> 4763.73 | E12: =C12-D12 -> 2036.27 | F12: =B12-E12 -> 1585873.4
A13: 47331 | B13: =F12 -> 1585873.4 | C13: =MIN(B13+D13,Finanzierung!$B$15/12) -> 6800 | D13: =ROUND(B13*Finanzierung!$B$13/12,2) -> 4757.62 | E13: =C13-D13 -> 2042.38 | F13: =B13-E13 -> 1583831
A14: 47362 | B14: =F13 -> 1583831 | C14: =MIN(B14+D14,Finanzierung!$B$15/12) -> 6800 | D14: =ROUND(B14*Finanzierung!$B$13/12,2) -> 4751.49 | E14: =C14-D14 -> 2048.51 | F14: =B14-E14 -> 1581782.5
A15: 47392 | B15: =F14 -> 1581782.5 | C15: =MIN(B15+D15,Finanzierung!$B$15/12) -> 6800 | D15: =ROUND(B15*Finanzierung!$B$13/12,2) -> 4745.35 | E15: =C15-D15 -> 2054.65 | F15: =B15-E15 -> 1579727.8
A16: 47423 | B16: =F15 -> 1579727.8 | C16: =MIN(B16+D16,Finanzierung!$B$15/12) -> 6800 | D16: =ROUND(B16*Finanzierung!$B$13/12,2) -> 4739.18 | E16: =C16-D16 -> 2060.82 | F16: =B16-E16 -> 1577667
A17: 47453 | B17: =F16 -> 1577667 | C17: =MIN(B17+D17,Finanzierung!$B$15/12) -> 6800 | D17: =ROUND(B17*Finanzierung!$B$13/12,2) -> 4733 | E17: =C17-D17 -> 2067 | F17: =B17-E17 -> 1575600
A18: 47484 | B18: =F17 -> 1575600 | C18: =MIN(B18+D18,Finanzierung!$B$15/12) -> 6800 | D18: =ROUND(B18*Finanzierung!$B$13/12,2) -> 4726.8 | E18: =C18-D18 -> 2073.2 | F18: =B18-E18 -> 1573526.8
... A65: 48914 | B65: =F64 -> 1471123.4 | C65: =MIN(B65+D65,Finanzierung!$B$15/12) -> 6800 | D65: =ROUND(B65*Finanzierung!$B$13/12,2) -> 4413.37 | E65: =C65-D65 -> 2386.63 | F65: =B65-E65 -> 1468736.8
A66: Summe 60 Monate | C66: =SUM(C6:C65) -> 408000 | D66: =SUM(D6:D65) -> 276736.78 | E66: =SUM(E6:E65) -> 131263.22 | F66: =F65 -> 1468736.8
A68: Quelle: 107 Darlehensvereinbarung; gleichbleibende Monatsrate bei sinkender Restschuld.
