Workbook

Sheet Offene Posten
A2: Rechnungen und Zahlungen
A3: Stichtag | B3: 47026
A5: Beleg | B5: Rechnungsdatum | C5: Beleg bis Stichtag | D5: Zahlung bis Stichtag | E5: Saldo EUR
A6: KP-2026-118 | B6: 46342 | C6: =SUMIFS(Belege!$G$6:$G$43,Belege!$A$6:$A$43,A6,Belege!$C$6:$C$43,"<="&$B$3) -> 450000 | D6: =SUMIFS(Bank!$D$6:$D$51,Bank!$C$6:$C$51,A6,Bank!$A$6:$A$51,"<="&$B$3) -> 450000 | E6: =C6-D6 -> 0
A7: GRE-26-816 | B7: 46346 | C7: =SUMIFS(Belege!$G$6:$G$43,Belege!$A$6:$A$43,A7,Belege!$C$6:$C$43,"<="&$B$3) -> 22500 | D7: =SUMIFS(Bank!$D$6:$D$51,Bank!$C$6:$C$51,A7,Bank!$A$6:$A$51,"<="&$B$3) -> 22500 | E7: =C7-D7 -> 0
A8: NF-26-118-139 | B8: 46378 | C8: =SUMIFS(Belege!$G$6:$G$43,Belege!$A$6:$A$43,A8,Belege!$C$6:$C$43,"<="&$B$3) -> 7850.51 | D8: =SUMIFS(Bank!$D$6:$D$51,Bank!$C$6:$C$51,A8,Bank!$A$6:$A$51,"<="&$B$3) -> 7850.51 | E8: =C8-D8 -> 0
A9: GB-26-778 | B9: 46379 | C9: =SUMIFS(Belege!$G$6:$G$43,Belege!$A$6:$A$43,A9,Belege!$C$6:$C$43,"<="&$B$3) -> 4047.5 | D9: =SUMIFS(Bank!$D$6:$D$51,Bank!$C$6:$C$51,A9,Bank!$A$6:$A$51,"<="&$B$3) -> 4047.5 | E9: =C9-D9 -> 0
A10: WG-26-104 | B10: 46330 | C10: =SUMIFS(Belege!$G$6:$G$43,Belege!$A$6:$A$43,A10,Belege!$C$6:$C$43,"<="&$B$3) -> 16065 | D10: =SUMIFS(Bank!$D$6:$D$51,Bank!$C$6:$C$51,A10,Bank!$A$6:$A$51,"<="&$B$3) -> 16065 | E10: =C10-D10 -> 0
A11: BA-27-328-K | B11: 46651 | C11: =SUMIFS(Belege!$G$6:$G$43,Belege!$A$6:$A$43,A11,Belege!$C$6:$C$43,"<="&$B$3) -> 4957.4 | D11: =SUMIFS(Bank!$D$6:$D$51,Bank!$C$6:$C$51,A11,Bank!$A$6:$A$51,"<="&$B$3) -> 4957.4 | E11: =C11-D11 -> 0
A12: BV-27-180 | B12: 46713 | C12: =SUMIFS(Belege!$G$6:$G$43,Belege!$A$6:$A$43,A12,Belege!$C$6:$C$43,"<="&$B$3) -> 9000 | D12: =SUMIFS(Bank!$D$6:$D$51,Bank!$C$6:$C$51,A12,Bank!$A$6:$A$51,"<="&$B$3) -> 9000 | E12: =C12-D12 -> 0
A13: LB-27-010 | B13: 46389 | C13: =SUMIFS(Belege!$G$6:$G$43,Belege!$A$6:$A$43,A13,Belege!$C$6:$C$43,"<="&$B$3) -> 10000 | D13: =SUMIFS(Bank!$D$6:$D$51,Bank!$C$6:$C$51,A13,Bank!$A$6:$A$51,"<="&$B$3) -> 10000 | E13: =C13-D13 -> 0
A14: LB-Z-2027 | B14: 46752 | C14: =SUMIFS(Belege!$G$6:$G$43,Belege!$A$6:$A$43,A14,Belege!$C$6:$C$43,"<="&$B$3) -> 28800 | D14: =SUMIFS(Bank!$D$6:$D$51,Bank!$C$6:$C$51,A14,Bank!$A$6:$A$51,"<="&$B$3) -> 28800 | E14: =C14-D14 -> 0
A15: LB-Z-2028 | B15: 47118 | C15: =SUMIFS(Belege!$G$6:$G$43,Belege!$A$6:$A$43,A15,Belege!$C$6:$C$43,"<="&$B$3) -> 0 | D15: =SUMIFS(Bank!$D$6:$D$51,Bank!$C$6:$C$51,A15,Bank!$A$6:$A$51,"<="&$B$3) -> 0 | E15: =C15-D15 -> 0
A16: KF-27-091 | B16: 46654 | C16: =SUMIFS(Belege!$G$6:$G$43,Belege!$A$6:$A$43,A16,Belege!$C$6:$C$43,"<="&$B$3) -> 46588.5 | D16: =SUMIFS(Bank!$D$6:$D$51,Bank!$C$6:$C$51,A16,Bank!$A$6:$A$51,"<="&$B$3) -> 46588.5 | E16: =C16-D16 -> 0
A17: KF-27-116 | B17: 46717 | C17: =SUMIFS(Belege!$G$6:$G$43,Belege!$A$6:$A$43,A17,Belege!$C$6:$C$43,"<="&$B$3) -> 67294.5 | D17: =SUMIFS(Bank!$D$6:$D$51,Bank!$C$6:$C$51,A17,Bank!$A$6:$A$51,"<="&$B$3) -> 67294.5 | E17: =C17-D17 -> 0
... A43: LE-PV-28-099 | B43: 47026 | C43: =SUMIFS(Belege!$G$6:$G$43,Belege!$A$6:$A$43,A43,Belege!$C$6:$C$43,"<="&$B$3) -> 45000 | D43: =SUMIFS(Bank!$D$6:$D$51,Bank!$C$6:$C$51,A43,Bank!$A$6:$A$51,"<="&$B$3) -> 0 | E43: =C43-D43 -> 45000
A44: Summe | C44: =SUM(C6:C43) -> 3190873.4 | D44: =SUM(D6:D43) -> 2208153.4 | E44: =SUM(E6:E43) -> 982720
A46: Positiver Saldo: noch nicht gezahlt; negativer Saldo: Zahlbetrag über Belegbetrag.
A47: Die Liste ersetzt keine fachliche Rechnungsfreigabe. Spätere Belege werden durch den Stichtag ausgeschlossen.

Sheet Belege
A2: Projektbelege
A3: SW-HI-26-08 · Beträge in EUR
A5: Beleg | B5: KG | C5: Datum | D5: Leistung | E5: Netto EUR | F5: USt EUR | G5: Brutto EUR
A6: KP-2026-118 | B6: 100 | C6: 46342 | D6: Kaufpreisfälligkeit Grundstück | E6: 450000 | F6: 0 | G6: =SUM(E6:F6) -> 450000
A7: GRE-26-816 | B7: 100 | C7: 46346 | D7: Grunderwerbsteuerbescheid | E7: 22500 | F7: 0 | G7: =SUM(E7:F7) -> 22500
A8: NF-26-118-139 | B8: 100 | C8: 46378 | D8: Notarkostenberechnung Grundstückskauf und Grundschuld | E8: 6598.5 | F8: 1252.01 | G8: =SUM(E8:F8) -> 7850.51
A9: GB-26-778 | B9: 100 | C9: 46379 | D9: Gerichtskostenrechnung Grundbuch | E9: 4047.5 | F9: 0 | G9: =SUM(E9:F9) -> 4047.5
A10: WG-26-104 | B10: 100 | C10: 46330 | D10: Grundstücksvermittlung | E10: 13500 | F10: 2565 | G10: =SUM(E10:F10) -> 16065
A11: BA-27-328-K | B11: 700 | C11: 46651 | D11: Kostenbescheid zum Bauantrag | E11: 4957.4 | F11: 0 | G11: =SUM(E11:F11) -> 4957.4
A12: BV-27-180 | B12: 700 | C12: 46713 | D12: Beitragsrechnung Bauleistungs- und Bauherrenhaftpflichtversicherung | E12: 9000 | F12: 0 | G12: =SUM(E12:F12) -> 9000
A13: LB-27-010 | B13: 800 | C13: 46389 | D13: Vereinbartes Finanzierungsentgelt | E13: 10000 | F13: 0 | G13: =SUM(E13:F13) -> 10000
A14: LB-Z-2027 | B14: 800 | C14: 46752 | D14: Darlehenszinsen 2027 | E14: 28800 | F14: 0 | G14: =SUM(E14:F14) -> 28800
A15: LB-Z-2028 | B15: 800 | C15: 47118 | D15: Darlehenszinsen 2028 | E15: 51200 | F15: 0 | G15: =SUM(E15:F15) -> 51200
A16: KF-27-091 | B16: 700 | C16: 46654 | D16: Objektplanung LPH 1 bis 4 | E16: 39150 | F16: 7438.5 | G16: =SUM(E16:F16) -> 46588.5
A17: KF-27-116 | B17: 700 | C17: 46717 | D17: Objektplanung LPH 5 bis 7 | E17: 56550 | F17: 10744.5 | G17: =SUM(E17:F17) -> 67294.5
... A43: LE-PV-28-099 | B43: 400 | C43: 47026 | D43: PV-Anlage Lieferung und Montage | E43: 45000 | F43: 0 | G43: =SUM(E43:F43) -> 45000
A44: Summe | E44: =SUM(E6:E43) -> 3026103.4 | F44: =SUM(F6:F43) -> 456112.01 | G44: =SUM(G6:G43) -> 3482215.4
A46: Quelle: Einzelbelege 70–106 und 119; Rechnungskorrekturen sind negativ.

Sheet Bank
A2: Projektkonto 882608
A3: SW-HI-26-08 · Beträge in EUR
A5: Valuta | B5: Bankreferenz | C5: Beleg / Herkunft | D5: Zahlung EUR | E5: Zufluss Mittel | F5: Kontosaldo EUR
A6: 46341 | B6: EK-20261115 | C6: EK | D6: 0 | E6: 800000 | F6: =E6-D6 -> 800000
A7: 46344 | B7: SW-74-20261118 | C7: WG-26-104 | D7: 16065 | E7: 0 | F7: =F6+E7-D7 -> 783935
A8: 46353 | B8: SW-70-20261127 | C8: KP-2026-118 | D8: 450000 | E8: 0 | F8: =F7+E8-D8 -> 333935
A9: 46364 | B9: SW-71-20261208 | C9: GRE-26-816 | D9: 22500 | E9: 0 | F9: =F8+E9-D9 -> 311435
A10: 46388 | B10: DL-20270101 | C10: Darlehen | D10: 0 | E10: 400000 | F10: =F9+E10-D10 -> 711435
A11: 46392 | B11: SW-72-20270105 | C11: NF-26-118-139 | D11: 7850.51 | E11: 0 | F11: =F10+E11-D11 -> 703584.49
A12: 46393 | B12: SW-73-20270106 | C12: GB-26-778 | D12: 4047.5 | E12: 0 | F12: =F11+E12-D12 -> 699536.99
A13: 46402 | B13: EK-20270115 | C13: EK | D13: 0 | E13: 700000 | F13: =F12+E13-D13 -> 1399537
A14: 46403 | B14: SW-77-20270116 | C14: LB-27-010 | D14: 10000 | E14: 0 | F14: =F13+E14-D14 -> 1389537
A15: 46419 | B15: SW-88-20270201 | C15: BP-27-018 | D15: 14280 | E15: 0 | F15: =F14+E15-D15 -> 1375257
A16: 46569 | B16: DL-20270701 | C16: Darlehen | D16: 0 | E16: 400000 | F16: =F15+E16-D16 -> 1775257
A17: 46661 | B17: DL-20271001 | C17: Darlehen | D17: 0 | E17: 800000 | F17: =F16+E17-D17 -> 2575257
A18: 46665 | B18: SW-75-20271005 | C18: BA-27-328-K | D18: 4957.4 | E18: 0 | F18: =F17+E18-D18 -> 2570299.6
... A51: 48852 | B51: SW-83-20330930 | C51: KF-33-092 | D51: 3451 | E51: 0 | F51: =F50+E51-D51 -> 217784.59
A53: Quelle: vollständige Projektkontoauszüge 109–112; Erstattungen als negative Zahlungen.
